psquared_consume/__init__.py
psquared_consume/consumption.py
psquared_consume/execution_request.py
psquared_consume/mock_server.py
psquared_consume/pp_execute.py
psquared_consume/psquared_engine.py
psquared_consume/utils.py
psquared_consume-1.0.2.dist-info/LICENSE.txt
psquared_consume-1.0.2.dist-info/METADATA
psquared_consume-1.0.2.dist-info/WHEEL
psquared_consume-1.0.2.dist-info/entry_points.txt
psquared_consume-1.0.2.dist-info/top_level.txt
psquared_consume-1.0.2.dist-info/RECORD
