Metadata-Version: 2.1
Name: psquared-consume
Version: 1.0.2
Summary: Consumes PSquared execution requests from a RabbitMQ queue.
Author-email: Simon Patton <sjpatton@lbl.gov>
License: BSD-3-Clause-LBNL
Keywords: rabbitmq,rabbitmq_consume
Classifier: Development Status :: 3 - Alpha
Classifier: Intended Audience :: Developers
Classifier: Topic :: Scientific/Engineering
Classifier: Programming Language :: Python :: 3.10
Requires-Python: <4,>=3.10
License-File: LICENSE.txt
Requires-Dist: rabbitmq-consume (>=1.0)
Requires-Dist: requests (>2.28)
